Metadata-Version: 1.0
Name: Products.PloneHotfix20110720
Version: 1.2
Summary: Plone security hotfix addressing CVE 2011-0720
Home-page: http://plone.org/products/plone/security/advisories/cve-2011-0720
Author: Plone security team
Author-email: security@plone.org
License: GPL
Keywords: security hotfix patch
Platform: UNKNOWN
Classifier: Programming Language :: Python
Classifier: Framework :: Plone
Classifier: Framework :: Zope2
